deeppy/__init__.py
deeppy/progress.py
deep_py-0.0.4.dist-info/LICENSE
deep_py-0.0.4.dist-info/METADATA
deep_py-0.0.4.dist-info/WHEEL
deep_py-0.0.4.dist-info/top_level.txt
deep_py-0.0.4.dist-info/RECORD
