Metadata-Version: 2.1
Name: deep-py
Version: 0.0.4
Summary: Python library for Data Science
Home-page: https://github.com/andrusyak/deep-py.git
Author: Ruslan Andrusyak
License: UNKNOWN
Platform: UNKNOWN
Classifier: Programming Language :: Python :: 3
Classifier: License :: OSI Approved :: MIT License
Classifier: Operating System :: OS Independent
Requires-Python: >=3.6
